dojo_openenv/__about__.py
dojo_openenv/__init__.py
dojo_openenv/dojo.py
dojo_openenv/models.py
dojo_openenv-0.1.4.dist-info/METADATA
dojo_openenv-0.1.4.dist-info/WHEEL
dojo_openenv-0.1.4.dist-info/RECORD
