Metadata-Version: 2.4
Name: dojo-openenv
Version: 0.1.4
Summary: Wrapper for dojo-sdk-client to use with OpenEnv
Requires-Python: >=3.9
Requires-Dist: dojo-sdk-client>=0.1.7
Requires-Dist: dojo-sdk-core>=0.1.11
Requires-Dist: openenv-core>=0.1.0
Provides-Extra: dev
Requires-Dist: ruff; extra == 'dev'
